watchdog/__init__.py
watchdog/watchdog.py
cxzoolwatchdog-0.0.5.dist-info/LICENSE
cxzoolwatchdog-0.0.5.dist-info/METADATA
cxzoolwatchdog-0.0.5.dist-info/WHEEL
cxzoolwatchdog-0.0.5.dist-info/top_level.txt
cxzoolwatchdog-0.0.5.dist-info/RECORD
