Metadata-Version: 2.1
Name: cxzoolwatchdog
Version: 0.0.5
Summary: A small example package
Home-page: https://github.com/ruanzq/watchdog
Author: cxzool
Author-email: 954542623@qq.com
License: UNKNOWN
Platform: UNKNOWN
Classifier: Programming Language :: Python :: 3
Classifier: License :: OSI Approved :: MIT License
Classifier: Operating System :: OS Independent
Requires-Dist: argparse
